billit/__init__.py
billit/auth.py
billit/client.py
billit/constants.py
billit/error.py
billit/utils/__init__.py
billit/utils/tax_utils.py
billit-0.3.0.dist-info/LICENSE
billit-0.3.0.dist-info/WHEEL
billit-0.3.0.dist-info/METADATA
billit-0.3.0.dist-info/RECORD
