Metadata-Version: 2.1
Name: billit
Version: 0.3.0
Summary: Python SDK for https://billit.io
License: MIT
Author: Paris Kasidiaris
Author-email: paris@withlogic.co
Requires-Python: >=3.8,<4.0
Classifier: License :: OSI Approved :: MIT License
Classifier: Programming Language :: Python :: 3
Classifier: Programming Language :: Python :: 3.10
Classifier: Programming Language :: Python :: 3.8
Classifier: Programming Language :: Python :: 3.9
Requires-Dist: requests (>=2.27.1,<3.0.0)
Requires-Dist: types-requests (>=2.28.0,<3.0.0)
